black_knight/__init__.py
black_knight/apps.py
black_knight/admin/__init__.py
black_knight/admin/actions.py
black_knight/admin/apps.py
black_knight/admin/models.py
black_knight/admin/options.py
black_knight/admin/sites.py
black_knight/admin/utils/__init__.py
black_knight/admin/utils/brace.py
black_knight/admin/utils/request.py
black_knight/admin/utils/response.py
black_knight/fields/__init__.py
black_knight/fields/base.py
black_knight/fields/datetime.py
black_knight/fields/files.py
black_knight/fields/number.py
black_knight/fields/related.py
black_knight/fields/text.py
black_knight/static/black_knight/default_avatar.jpg
black_knight/static/black_knight/dist/App.d.ts
black_knight/static/black_knight/dist/App.d.ts.map
black_knight/static/black_knight/dist/App.d.ts.map.gz
black_knight/static/black_knight/dist/Dashboard.1fd69a091a64d91d70e2.js
black_knight/static/black_knight/dist/Dashboard.1fd69a091a64d91d70e2.js.gz
black_knight/static/black_knight/dist/Dashboard.css
black_knight/static/black_knight/dist/Dashboard.css.gz
black_knight/static/black_knight/dist/Login.6ef159725f42d1ed0804.js
black_knight/static/black_knight/dist/Login.6ef159725f42d1ed0804.js.gz
black_knight/static/black_knight/dist/Login.css
black_knight/static/black_knight/dist/Login.css.gz
black_knight/static/black_knight/dist/components.css
black_knight/static/black_knight/dist/components.css.gz
black_knight/static/black_knight/dist/components.dc1030a71f26fa7919e0.js
black_knight/static/black_knight/dist/components.dc1030a71f26fa7919e0.js.gz
black_knight/static/black_knight/dist/index.d.ts
black_knight/static/black_knight/dist/index.d.ts.map
black_knight/static/black_knight/dist/main.1e10a7ef50b0368483e8.js
black_knight/static/black_knight/dist/main.1e10a7ef50b0368483e8.js.gz
black_knight/static/black_knight/dist/main.css
black_knight/static/black_knight/dist/main.css.gz
black_knight/static/black_knight/dist/react_vendors.d53fcf6e1a399ff5983c.js
black_knight-0.4.1.dist-info/LICENSE
black_knight-0.4.1.dist-info/METADATA
black_knight-0.4.1.dist-info/WHEEL
black_knight-0.4.1.dist-info/top_level.txt
black_knight-0.4.1.dist-info/zip-safe
black_knight-0.4.1.dist-info/RECORD
