Metadata-Version: 2.1
Name: black-knight
Version: 0.4.1
Summary: Django Admin Skin-ish
Home-page: https://github.com/00-team/black-knight
Author: 00 Team
Author-email: 00.team.mail@gmail.com
License: GPL-3.0
Project-URL: Source, https://github.com/00-team/black-knight/
Project-URL: Tracker, https://github.com/00-team/black-knight/issues
Classifier: Development Status :: 3 - Alpha
Classifier: Environment :: Web Environment
Classifier: Framework :: Django
Classifier: Framework :: Django :: 4.0
Classifier: Intended Audience :: Developers
Classifier: License :: OSI Approved :: GNU General Public License v3 (GPLv3)
Classifier: Natural Language :: English
Classifier: Operating System :: OS Independent
Classifier: Programming Language :: Python :: 3.10
Classifier: Topic :: Internet
Classifier: Topic :: Internet :: WWW/HTTP
Classifier: Topic :: Internet :: WWW/HTTP :: Site Management
Requires-Python: >=3.10
License-File: LICENSE
Requires-Dist: Django (>=4.0)
